Workbook

Sheet 07_Dashboard
A1: Dashboard
A4: Total SKUs | B4: Invest | C4: Retain | D4: Test | E4: Remove | F4: Sales at risk | G4: Upside opportunity | H4: Avg. score
A5: =COUNTA('03_Scoring_Model'!$A$4:$A$15) -> 12 | B5: =COUNTIF('03_Scoring_Model'!$S$4:$S$15,"Invest") -> 2 | C5: =COUNTIF('03_Scoring_Model'!$S$4:$S$15,"Retain") -> 3 | D5: =COUNTIF('03_Scoring_Model'!$S$4:$S$15,"Test") -> 4 | E5: =COUNTIF('03_Scoring_Model'!$S$4:$S$15,"Remove") -> 3 | F5: =SUMIF('03_Scoring_Model'!$S$4:$S$15,"Remove",'03_Scoring_Model'!$D$4:$D$15)/1000 -> 425 | G5: =(SUMIF('03_Scoring_Model'!$S$4:$S$15,"Invest",'03_Scoring_Model'!$D$4:$D$15)*15%+SUMIF('03_Scoring_Model'!$S$4:$S$15,"Test",'03_Scoring_Model'!$D$4:$D$15)*8%)/1000 -> 179.55 | H5: =AVERAGE('03_Scoring_Model'!$P$4:$P$15) -> 56.916667
A6: Decision model | B6: High-priority scale plays | C6: Stable range | D6: Controlled bets | E6: Tail rationalisation | F6: Remove-classified sales (EUR k) | G6: Invest/Test uplift proxy (EUR k) | H6: Portfolio health
A10: Recommendation | B10: SKU Count | C10: Net Sales | E10: Sample SKU | F10: Rate of Sale | G10: Gross Margin % | H10: Net Sales
A11: ="Invest" -> Invest | B11: =COUNTIF('03_Scoring_Model'!$S$4:$S$15,A11) -> 2 | C11: =SUMIF('03_Scoring_Model'!$S$4:$S$15,A11,'03_Scoring_Model'!$D$4:$D$15) -> 725000 | E11: ='01_SKU_Input'!B4 -> Aura Chocolates Travel Gift Box 300g | F11: ='01_SKU_Input'!L4 -> 72 | G11: ='01_SKU_Input'!I4 -> 0.58 | H11: ='01_SKU_Input'!H4 -> 420000
A12: ="Retain" -> Retain | B12: =COUNTIF('03_Scoring_Model'!$S$4:$S$15,A12) -> 3 | C12: =SUMIF('03_Scoring_Model'!$S$4:$S$15,A12,'03_Scoring_Model'!$D$4:$D$15) -> 1145000 | E12: ='01_SKU_Input'!B5 -> Northgate Whisky Reserve 1L | F12: ='01_SKU_Input'!L5 -> 46 | G12: ='01_SKU_Input'!I5 -> 0.62 | H12: ='01_SKU_Input'!H5 -> 510000
A13: ="Test" -> Test | B13: =COUNTIF('03_Scoring_Model'!$S$4:$S$15,A13) -> 4 | C13: =SUMIF('03_Scoring_Model'!$S$4:$S$15,A13,'03_Scoring_Model'!$D$4:$D$15) -> 885000 | E13: ='01_SKU_Input'!B6 -> Vela Skin Hydration Travel Duo | F13: ='01_SKU_Input'!L6 -> 54 | G13: ='01_SKU_Input'!I6 -> 0.64 | H13: ='01_SKU_Input'!H6 -> 360000
A14: ="Remove" -> Remove | B14: =COUNTIF('03_Scoring_Model'!$S$4:$S$15,A14) -> 3 | C14: =SUMIF('03_Scoring_Model'!$S$4:$S$15,A14,'03_Scoring_Model'!$D$4:$D$15) -> 425000 | E14: ='01_SKU_Input'!B7 -> Pulse Energy Multipack 6x250ml | F14: ='01_SKU_Input'!L7 -> 88 | G14: ='01_SKU_Input'!I7 -> 0.36 | H14: ='01_SKU_Input'!H7 -> 210000
E15: ='01_SKU_Input'!B8 -> Solara SPF Travel Kit | F15: ='01_SKU_Input'!L8 -> 39 | G15: ='01_SKU_Input'!I8 -> 0.55 | H15: ='01_SKU_Input'!H8 -> 295000
E16: ='01_SKU_Input'!B9 -> Terra Coffee Premium Tin 250g | F16: ='01_SKU_Input'!L9 -> 28 | G16: ='01_SKU_Input'!I9 -> 0.43 | H16: ='01_SKU_Input'!H9 -> 180000

Sheet 01_SKU_Input
A1: SKU Input
A3: SKU ID | B3: SKU Name | C3: Category | D3: Segment | E3: Pack Format | F3: Size | G3: Price | H3: Net Sales | I3: Gross Margin % | J3: Gross Margin Value | K3: Units Sold | L3: Rate of Sale | M3: Distribution % | N3: Avg. Facings | O3: Traveller Occasion | P3: Core Traveller Type | Q3: Cannibalisation Risk | R3: Strategic Role | S3: Current Support Level | T3: Notes
A4: SKU 01 | B4: Aura Chocolates Travel Gift Box 300g | C4: Confectionery | D4: Gifting | E4: Gift box | F4: 300g | G4: 18.5 | H4: 420000 | I4: 0.58 | J4: =H4*I4 -> 243600 | K4: 22703 | L4: 72 | M4: 0.68 | N4: 4 | O4: Gift | P4: Leisure | Q4: Low | R4: Hero | S4: High | T4: Strong airport gifting fit and high browse value
A5: SKU 02 | B5: Northgate Whisky Reserve 1L | C5: Spirits | D5: Premium | E5: Travel exclusive | F5: 1L | G5: 49.9 | H5: 510000 | I5: 0.62 | J5: =H5*I5 -> 316200 | K5: 10220 | L5: 46 | M5: 0.74 | N5: 3 | O5: Premium treat | P5: Business | Q5: Medium | R5: Margin builder | S5: High | T5: High value but needs visibility in gifting-heavy stores
A6: SKU 03 | B6: Vela Skin Hydration Travel Duo | C6: Beauty | D6: Premium | E6: Duo | F6: 2x50ml | G6: 32 | H6: 360000 | I6: 0.64 | J6: =H6*I6 -> 230400 | K6: 11250 | L6: 54 | M6: 0.52 | N6: 3 | O6: Replenishment | P6: Long-haul | Q6: Low | R6: Premiumiser | S6: Medium | T6: Strong travel need-state with distribution headroom
A7: SKU 04 | B7: Pulse Energy Multipack 6x250ml | C7: Beverage | D7: Mainstream | E7: Multipack | F7: 6x250ml | G7: 9.5 | H7: 210000 | I7: 0.36 | J7: =H7*I7 -> 75600 | K7: 22105 | L7: 88 | M7: 0.82 | N7: 5 | O7: Impulse | P7: Gen Z | Q7: High | R7: Traffic driver | S7: Medium | T7: Good units but low margin and risk of replacing higher-value beverages
A8: SKU 05 | B8: Solara SPF Travel Kit | C8: Beauty | D8: Travel need | E8: Travel kit | F8: 3-piece | G8: 24 | H8: 295000 | I8: 0.55 | J8: =H8*I8 -> 162250 | K8: 12292 | L8: 39 | M8: 0.48 | N8: 2 | O8: Replenishment | P8: Family | Q8: Low | R8: Recruitment SKU | S8: Low | T8: Clear travel pain point but under-distributed
A9: SKU 06 | B9: Terra Coffee Premium Tin 250g | C9: Food | D9: Premium | E9: Tin | F9: 250g | G9: 12 | H9: 180000 | I9: 0.43 | J9: =H9*I9 -> 77400 | K9: 15000 | L9: 28 | M9: 0.58 | N9: 2 | O9: Destination-linked purchase | P9: Leisure | Q9: Medium | R9: Seasonal/test SKU | S9: Low | T9: Could work as destination-linked souvenir if supported
A10: SKU 07 | B10: Botanika Mini Fragrance Set | C10: Beauty | D10: Discovery | E10: Mini set | F10: 5x8ml | G10: 39 | H10: 245000 | I10: 0.67 | J10: =H10*I10 -> 164150 | K10: 6282 | L10: 31 | M10: 0.34 | N10: 2 | O10: Discovery/trial | P10: Gen Z | Q10: Low | R10: Recruitment SKU | S10: Low | T10: High strategic fit; needs airport test before scaling
A11: SKU 08 | B11: Frost Mints Pocket Pack | C11: Confectionery | D11: Value | E11: Single | F11: 40g | G11: 2.5 | H11: 95000 | I11: 0.29 | J11: =H11*I11 -> 27550 | K11: 38000 | L11: 64 | M11: 0.91 | N11: 6 | O11: Impulse | P11: Domestic | Q11: High | R11: Traffic driver | S11: Low | T11: High reach but weak economics and limited distinctiveness
A12: SKU 09 | B12: Altitude Protein Bar 12-pack | C12: Snacks | D12: Health | E12: Multipack | F12: 12-pack | G12: 16 | H12: 165000 | I12: 0.41 | J12: =H12*I12 -> 67650 | K12: 10313 | L12: 22 | M12: 0.44 | N12: 2 | O12: Business travel | P12: Business | Q12: Medium | R12: Seasonal/test SKU | S12: Low | T12: Potential for business travel but current performance is soft
A13: SKU 10 | B13: Mare RTD Cocktail 4x200ml | C13: Beverage | D13: Premium | E13: Travel exclusive | F13: 4x200ml | G13: 17 | H13: 305000 | I13: 0.51 | J13: =H13*I13 -> 155550 | K13: 17941 | L13: 57 | M13: 0.39 | N13: 3 | O13: Gift | P13: Leisure | Q13: Low | R13: Premiumiser | S13: Medium | T13: Travel-exclusive format with strong conversion potential
A14: SKU 11 | B14: Lumina Beauty Refill Pouch | C14: Beauty | D14: Refill | E14: Refill | F14: 100ml | G14: 14 | H14: 120000 | I14: 0.48 | J14: =H14*I14 -> 57600 | K14: 8571 | L14: 18 | M14: 0.62 | N14: 2 | O14: Replenishment | P14: Long-haul | Q14: Medium | R14: Duplicative SKU | S14: Low | T14: Useful sustainability cue but overlaps with core beauty range
A15: SKU 12 | B15: Casa Roja Olive Oil Gift Tin | C15: Food | D15: Gifting | E15: Gift tin | F15: 500ml | G15: 22 | H15: 275000 | I15: 0.53 | J15: =H15*I15 -> 145750 | K15: 12500 | L15: 35 | M15: 0.46 | N15: 2 | O15: Destination-linked purchase | P15: Leisure | Q15: Low | R15: Margin builder | S15: Medium | T15: Giftable, destination-linked and margin-accretive

Sheet 02_Assumptions
A1: Assumptions
A3: Dimension | B3: Weight
A4: Sales Performance | B4: 0.2
A5: Margin Quality | B5: 0.2
A6: Rate of Sale | B6: 0.15
A7: Distribution Opportunity | B7: 0.15
A8: Occasion Fit | B8: 0.1
A9: Strategic Role | B9: 0.1
A10: Cannibalisation Risk Penalty | B10: -0.1
A13: Strategic role | B13: Score | C13: Interpretation
A14: Hero | B14: 5 | C14: Core range anchor
A15: Margin builder | B15: 5 | C15: Profit-led portfolio role
A16: Premiumiser | B16: 4 | C16: Raises category perception
A17: Recruitment SKU | B17: 4 | C17: Brings new shoppers or missions
A18: Traffic driver | B18: 3 | C18: Useful volume role
A19: Seasonal/test SKU | B19: 3 | C19: Worth controlled testing
A20: Duplicative SKU | B20: 1 | C20: Weak distinctiveness
A22: Sales threshold | B22: Score | C22: Definition
A23: 350000 | B23: 5 | C23: Large revenue contributor
A24: 260000 | B24: 4 | C24: Strong revenue contributor
A25: 170000 | B25: 3 | C25: Mid-tier performer
A26: 100000 | B26: 2 | C26: Low performer
A27: 0 | B27: 1 | C27: Tail SKU
A30: Cannibalisation Risk | B30: Penalty | C30: Interpretation
A31: Low | B31: 0 | C31: Distinct mission or incremental occasion
A32: Medium | B32: -5 | C32: Some overlap with existing SKU
A33: High | B33: -10 | C33: Likely substitution or duplicate
A35: Margin threshold | B35: Score | C35: Definition
A36: 0.6 | B36: 5 | C36: 60%+
A37: 0.5 | B37: 4 | C37: 50-59%
A38: 0.4 | B38: 3 | C38: 40-49%
A39: 0.3 | B39: 2 | C39: 30-39%
A40: 0 | B40: 1 | C40: Below 30%
A42: Recommendation | B42: Minimum Score | C42: Primary logic
A43: Invest | B43: 65 | C43: High total score, margin, ROS and role clarity
A44: Retain | B44: 50 | C44: Solid economics with stable portfolio role
A45: Test | B45: 50 | C45: Medium score plus strategic fit or distribution headroom
A46: Remove | B46: 0 | C46: Weak economics, low role clarity or high cannibalisation

Sheet 03_Scoring_Model
A1: Scoring Model
A3: SKU ID | B3: SKU Name | C3: Category | D3: Net Sales | E3: GM % | F3: Rate of Sale | G3: Distribution % | H3: Strategic Role | I3: Sales Score | J3: Margin Score | K3: ROS Score | L3: Distribution Opp. | M3: Occasion Fit | N3: Role Score | O3: Cannibal Penalty | P3: Total Score | Q3: Commercial Perf. | R3: Strategic Attr. | S3: Recommendation | T3: Quadrant
A4: ='01_SKU_Input'!A4 -> SKU 01 | B4: ='01_SKU_Input'!B4 -> Aura Chocolates Travel Gift Box 300g | C4: ='01_SKU_Input'!C4 -> Confectionery | D4: ='01_SKU_Input'!H4 -> 420000 | E4: ='01_SKU_Input'!I4 -> 0.58 | F4: ='01_SKU_Input'!L4 -> 72 | G4: ='01_SKU_Input'!M4 -> 0.68 | H4: ='01_SKU_Input'!R4 -> Hero | I4: =IF(D4>=350000,5,IF(D4>=260000,4,IF(D4>=170000,3,IF(D4>=100000,2,1)))) -> 5 | J4: =IF(E4>=60%,5,IF(E4>=50%,4,IF(E4>=40%,3,IF(E4>=30%,2,1)))) -> 4 | K4: =IF(F4>=75,5,IF(F4>=55,4,IF(F4>=35,3,IF(F4>=20,2,1)))) -> 4 | L4: =IF(AND(K4>=4,G4<60%),5,IF(AND(K4>=4,G4<80%),4,IF(AND(K4>=3,G4<80%),3,IF(AND(K4<=2,G4>=75%),2,1)))) -> 4 | M4: =IF(OR(ISNUMBER(SEARCH("Gift",'01_SKU_Input'!O4)),ISNUMBER(SEARCH("travel",'01_SKU_Input'!O4)),ISNUMBER(SEARCH("Premium",'01_SKU_Input'!O4)),ISNUMBER(SEARCH("Discovery",'01_SKU_Input'!O4)),ISNUMBER(SEARCH("Destination",'01_SKU_Input'!O4))),5,IF(OR(ISNUMBER(SEARCH("Impulse",'01_SKU_Input'!O4)),ISNUMBER(SEARCH("Replenishment",'01_SKU_Input'!O4)),ISNUMBER(SEARCH("Business",'01_SKU_Input'!O4))),4,3)) -> 5 | N4: =IF(H4="Hero",5,IF(H4="Margin builder",5,IF(H4="Premiumiser",4,IF(H4="Recruitment SKU",4,IF(H4="Traffic driver",3,IF(H4="Seasonal/test SKU",3,1)))))) -> 5 | O4: =IF('01_SKU_Input'!Q4="High",-10,IF('01_SKU_Input'!Q4="Medium",-5,0)) -> 0 | P4: =I4*'02_Assumptions'!$B$4/5*100+J4*'02_Assumptions'!$B$5/5*100+K4*'02_Assumptions'!$B$6/5*100+L4*'02_Assumptions'!$B$7/5*100+M4*'02_Assumptions'!$B$8/5*100+N4*'02_Assumptions'!$B$9/5*100+O4 -> 80 | Q4: =I4*20/5+J4*20/5+K4*15/5 -> 48 | R4: =L4*15/5+M4*10/5+N4*10/5+O4 -> 32 | S4: =IF(AND(P4>=65,J4>=4,K4>=4,O4>=-5),"Invest",IF(AND(P4>=40,G4<60%,OR(H4="Recruitment SKU",H4="Seasonal/test SKU")),"Test",IF(P4>=50,"Retain","Remove"))) -> Invest | T4: =IF(AND(Q4>=35,R4>=20),"Winners",IF(AND(Q4>=35,R4<20),"Efficient but not priority",IF(AND(Q4<35,R4>=20),"Potential bets","Weak tail"))) -> Winners
A5: ='01_SKU_Input'!A5 -> SKU 02 | B5: ='01_SKU_Input'!B5 -> Northgate Whisky Reserve 1L | C5: ='01_SKU_Input'!C5 -> Spirits | D5: ='01_SKU_Input'!H5 -> 510000 | E5: ='01_SKU_Input'!I5 -> 0.62 | F5: ='01_SKU_Input'!L5 -> 46 | G5: ='01_SKU_Input'!M5 -> 0.74 | H5: ='01_SKU_Input'!R5 -> Margin builder | I5: =IF(D5>=350000,5,IF(D5>=260000,4,IF(D5>=170000,3,IF(D5>=100000,2,1)))) -> 5 | J5: =IF(E5>=60%,5,IF(E5>=50%,4,IF(E5>=40%,3,IF(E5>=30%,2,1)))) -> 5 | K5: =IF(F5>=75,5,IF(F5>=55,4,IF(F5>=35,3,IF(F5>=20,2,1)))) -> 3 | L5: =IF(AND(K5>=4,G5<60%),5,IF(AND(K5>=4,G5<80%),4,IF(AND(K5>=3,G5<80%),3,IF(AND(K5<=2,G5>=75%),2,1)))) -> 3 | M5: =IF(OR(ISNUMBER(SEARCH("Gift",'01_SKU_Input'!O5)),ISNUMBER(SEARCH("travel",'01_SKU_Input'!O5)),ISNUMBER(SEARCH("Premium",'01_SKU_Input'!O5)),ISNUMBER(SEARCH("Discovery",'01_SKU_Input'!O5)),ISNUMBER(SEARCH("Destination",'01_SKU_Input'!O5))),5,IF(OR(ISNUMBER(SEARCH("Impulse",'01_SKU_Input'!O5)),ISNUMBER(SEARCH("Replenishment",'01_SKU_Input'!O5)),ISNUMBER(SEARCH("Business",'01_SKU_Input'!O5))),4,3)) -> 5 | N5: =IF(H5="Hero",5,IF(H5="Margin builder",5,IF(H5="Premiumiser",4,IF(H5="Recruitment SKU",4,IF(H5="Traffic driver",3,IF(H5="Seasonal/test SKU",3,1)))))) -> 5 | O5: =IF('01_SKU_Input'!Q5="High",-10,IF('01_SKU_Input'!Q5="Medium",-5,0)) -> -5 | P5: =I5*'02_Assumptions'!$B$4/5*100+J5*'02_Assumptions'!$B$5/5*100+K5*'02_Assumptions'!$B$6/5*100+L5*'02_Assumptions'!$B$7/5*100+M5*'02_Assumptions'!$B$8/5*100+N5*'02_Assumptions'!$B$9/5*100+O5 -> 73 | Q5: =I5*20/5+J5*20/5+K5*15/5 -> 49 | R5: =L5*15/5+M5*10/5+N5*10/5+O5 -> 24 | S5: =IF(AND(P5>=65,J5>=4,K5>=4,O5>=-5),"Invest",IF(AND(P5>=40,G5<60%,OR(H5="Recruitment SKU",H5="Seasonal/test SKU")),"Test",IF(P5>=50,"Retain","Remove"))) -> Retain | T5: =IF(AND(Q5>=35,R5>=20),"Winners",IF(AND(Q5>=35,R5<20),"Efficient but not priority",IF(AND(Q5<35,R5>=20),"Potential bets","Weak tail"))) -> Winners
A6: ='01_SKU_Input'!A6 -> SKU 03 | B6: ='01_SKU_Input'!B6 -> Vela Skin Hydration Travel Duo | C6: ='01_SKU_Input'!C6 -> Beauty | D6: ='01_SKU_Input'!H6 -> 360000 | E6: ='01_SKU_Input'!I6 -> 0.64 | F6: ='01_SKU_Input'!L6 -> 54 | G6: ='01_SKU_Input'!M6 -> 0.52 | H6: ='01_SKU_Input'!R6 -> Premiumiser | I6: =IF(D6>=350000,5,IF(D6>=260000,4,IF(D6>=170000,3,IF(D6>=100000,2,1)))) -> 5 | J6: =IF(E6>=60%,5,IF(E6>=50%,4,IF(E6>=40%,3,IF(E6>=30%,2,1)))) -> 5 | K6: =IF(F6>=75,5,IF(F6>=55,4,IF(F6>=35,3,IF(F6>=20,2,1)))) -> 3 | L6: =IF(AND(K6>=4,G6<60%),5,IF(AND(K6>=4,G6<80%),4,IF(AND(K6>=3,G6<80%),3,IF(AND(K6<=2,G6>=75%),2,1)))) -> 3 | M6: =IF(OR(ISNUMBER(SEARCH("Gift",'01_SKU_Input'!O6)),ISNUMBER(SEARCH("travel",'01_SKU_Input'!O6)),ISNUMBER(SEARCH("Premium",'01_SKU_Input'!O6)),ISNUMBER(SEARCH("Discovery",'01_SKU_Input'!O6)),ISNUMBER(SEARCH("Destination",'01_SKU_Input'!O6))),5,IF(OR(ISNUMBER(SEARCH("Impulse",'01_SKU_Input'!O6)),ISNUMBER(SEARCH("Replenishment",'01_SKU_Input'!O6)),ISNUMBER(SEARCH("Business",'01_SKU_Input'!O6))),4,3)) -> 4 | N6: =IF(H6="Hero",5,IF(H6="Margin builder",5,IF(H6="Premiumiser",4,IF(H6="Recruitment SKU",4,IF(H6="Traffic driver",3,IF(H6="Seasonal/test SKU",3,1)))))) -> 4 | O6: =IF('01_SKU_Input'!Q6="High",-10,IF('01_SKU_Input'!Q6="Medium",-5,0)) -> 0 | P6: =I6*'02_Assumptions'!$B$4/5*100+J6*'02_Assumptions'!$B$5/5*100+K6*'02_Assumptions'!$B$6/5*100+L6*'02_Assumptions'!$B$7/5*100+M6*'02_Assumptions'!$B$8/5*100+N6*'02_Assumptions'!$B$9/5*100+O6 -> 74 | Q6: =I6*20/5+J6*20/5+K6*15/5 -> 49 | R6: =L6*15/5+M6*10/5+N6*10/5+O6 -> 25 | S6: =IF(AND(P6>=65,J6>=4,K6>=4,O6>=-5),"Invest",IF(AND(P6>=40,G6<60%,OR(H6="Recruitment SKU",H6="Seasonal/test SKU")),"Test",IF(P6>=50,"Retain","Remove"))) -> Retain | T6: =IF(AND(Q6>=35,R6>=20),"Winners",IF(AND(Q6>=35,R6<20),"Efficient but not priority",IF(AND(Q6<35,R6>=20),"Potential bets","Weak tail"))) -> Winners
A7: ='01_SKU_Input'!A7 -> SKU 04 | B7: ='01_SKU_Input'!B7 -> Pulse Energy Multipack 6x250ml | C7: ='01_SKU_Input'!C7 -> Beverage | D7: ='01_SKU_Input'!H7 -> 210000 | E7: ='01_SKU_Input'!I7 -> 0.36 | F7: ='01_SKU_Input'!L7 -> 88 | G7: ='01_SKU_Input'!M7 -> 0.82 | H7: ='01_SKU_Input'!R7 -> Traffic driver | I7: =IF(D7>=350000,5,IF(D7>=260000,4,IF(D7>=170000,3,IF(D7>=100000,2,1)))) -> 3 | J7: =IF(E7>=60%,5,IF(E7>=50%,4,IF(E7>=40%,3,IF(E7>=30%,2,1)))) -> 2 | K7: =IF(F7>=75,5,IF(F7>=55,4,IF(F7>=35,3,IF(F7>=20,2,1)))) -> 5 | L7: =IF(AND(K7>=4,G7<60%),5,IF(AND(K7>=4,G7<80%),4,IF(AND(K7>=3,G7<80%),3,IF(AND(K7<=2,G7>=75%),2,1)))) -> 1 | M7: =IF(OR(ISNUMBER(SEARCH("Gift",'01_SKU_Input'!O7)),ISNUMBER(SEARCH("travel",'01_SKU_Input'!O7)),ISNUMBER(SEARCH("Premium",'01_SKU_Input'!O7)),ISNUMBER(SEARCH("Discovery",'01_SKU_Input'!O7)),ISNUMBER(SEARCH("Destination",'01_SKU_Input'!O7))),5,IF(OR(ISNUMBER(SEARCH("Impulse",'01_SKU_Input'!O7)),ISNUMBER(SEARCH("Replenishment",'01_SKU_Input'!O7)),ISNUMBER(SEARCH("Business",'01_SKU_Input'!O7))),4,3)) -> 4 | N7: =IF(H7="Hero",5,IF(H7="Margin builder",5,IF(H7="Premiumiser",4,IF(H7="Recruitment SKU",4,IF(H7="Traffic driver",3,IF(H7="Seasonal/test SKU",3,1)))))) -> 3 | O7: =IF('01_SKU_Input'!Q7="High",-10,IF('01_SKU_Input'!Q7="Medium",-5,0)) -> -10 | P7: =I7*'02_Assumptions'!$B$4/5*100+J7*'02_Assumptions'!$B$5/5*100+K7*'02_Assumptions'!$B$6/5*100+L7*'02_Assumptions'!$B$7/5*100+M7*'02_Assumptions'!$B$8/5*100+N7*'02_Assumptions'!$B$9/5*100+O7 -> 42 | Q7: =I7*20/5+J7*20/5+K7*15/5 -> 35 | R7: =L7*15/5+M7*10/5+N7*10/5+O7 -> 7 | S7: =IF(AND(P7>=65,J7>=4,K7>=4,O7>=-5),"Invest",IF(AND(P7>=40,G7<60%,OR(H7="Recruitment SKU",H7="Seasonal/test SKU")),"Test",IF(P7>=50,"Retain","Remove"))) -> Remove | T7: =IF(AND(Q7>=35,R7>=20),"Winners",IF(AND(Q7>=35,R7<20),"Efficient but not priority",IF(AND(Q7<35,R7>=20),"Potential bets","Weak tail"))) -> Efficient but not priority
A8: ='01_SKU_Input'!A8 -> SKU 05 | B8: ='01_SKU_Input'!B8 -> Solara SPF Travel Kit | C8: ='01_SKU_Input'!C8 -> Beauty | D8: ='01_SKU_Input'!H8 -> 295000 | E8: ='01_SKU_Input'!I8 -> 0.55 | F8: ='01_SKU_Input'!L8 -> 39 | G8: ='01_SKU_Input'!M8 -> 0.48 | H8: ='01_SKU_Input'!R8 -> Recruitment SKU | I8: =IF(D8>=350000,5,IF(D8>=260000,4,IF(D8>=170000,3,IF(D8>=100000,2,1)))) -> 4 | J8: =IF(E8>=60%,5,IF(E8>=50%,4,IF(E8>=40%,3,IF(E8>=30%,2,1)))) -> 4 | K8: =IF(F8>=75,5,IF(F8>=55,4,IF(F8>=35,3,IF(F8>=20,2,1)))) -> 3 | L8: =IF(AND(K8>=4,G8<60%),5,IF(AND(K8>=4,G8<80%),4,IF(AND(K8>=3,G8<80%),3,IF(AND(K8<=2,G8>=75%),2,1)))) -> 3 | M8: =IF(OR(ISNUMBER(SEARCH("Gift",'01_SKU_Input'!O8)),ISNUMBER(SEARCH("travel",'01_SKU_Input'!O8)),ISNUMBER(SEARCH("Premium",'01_SKU_Input'!O8)),ISNUMBER(SEARCH("Discovery",'01_SKU_Input'!O8)),ISNUMBER(SEARCH("Destination",'01_SKU_Input'!O8))),5,IF(OR(ISNUMBER(SEARCH("Impulse",'01_SKU_Input'!O8)),ISNUMBER(SEARCH("Replenishment",'01_SKU_Input'!O8)),ISNUMBER(SEARCH("Business",'01_SKU_Input'!O8))),4,3)) -> 4 | N8: =IF(H8="Hero",5,IF(H8="Margin builder",5,IF(H8="Premiumiser",4,IF(H8="Recruitment SKU",4,IF(H8="Traffic driver",3,IF(H8="Seasonal/test SKU",3,1)))))) -> 4 | O8: =IF('01_SKU_Input'!Q8="High",-10,IF('01_SKU_Input'!Q8="Medium",-5,0)) -> 0 | P8: =I8*'02_Assumptions'!$B$4/5*100+J8*'02_Assumptions'!$B$5/5*100+K8*'02_Assumptions'!$B$6/5*100+L8*'02_Assumptions'!$B$7/5*100+M8*'02_Assumptions'!$B$8/5*100+N8*'02_Assumptions'!$B$9/5*100+O8 -> 66 | Q8: =I8*20/5+J8*20/5+K8*15/5 -> 41 | R8: =L8*15/5+M8*10/5+N8*10/5+O8 -> 25 | S8: =IF(AND(P8>=65,J8>=4,K8>=4,O8>=-5),"Invest",IF(AND(P8>=40,G8<60%,OR(H8="Recruitment SKU",H8="Seasonal/test SKU")),"Test",IF(P8>=50,"Retain","Remove"))) -> Test | T8: =IF(AND(Q8>=35,R8>=20),"Winners",IF(AND(Q8>=35,R8<20),"Efficient but not priority",IF(AND(Q8<35,R8>=20),"Potential bets","Weak tail"))) -> Winners
A9: ='01_SKU_Input'!A9 -> SKU 06 | B9: ='01_SKU_Input'!B9 -> Terra Coffee Premium Tin 250g | C9: ='01_SKU_Input'!C9 -> Food | D9: ='01_SKU_Input'!H9 -> 180000 | E9: ='01_SKU_Input'!I9 -> 0.43 | F9: ='01_SKU_Input'!L9 -> 28 | G9: ='01_SKU_Input'!M9 -> 0.58 | H9: ='01_SKU_Input'!R9 -> Seasonal/test SKU | I9: =IF(D9>=350000,5,IF(D9>=260000,4,IF(D9>=170000,3,IF(D9>=100000,2,1)))) -> 3 | J9: =IF(E9>=60%,5,IF(E9>=50%,4,IF(E9>=40%,3,IF(E9>=30%,2,1)))) -> 3 | K9: =IF(F9>=75,5,IF(F9>=55,4,IF(F9>=35,3,IF(F9>=20,2,1)))) -> 2 | L9: =IF(AND(K9>=4,G9<60%),5,IF(AND(K9>=4,G9<80%),4,IF(AND(K9>=3,G9<80%),3,IF(AND(K9<=2,G9>=75%),2,1)))) -> 1 | M9: =IF(OR(ISNUMBER(SEARCH("Gift",'01_SKU_Input'!O9)),ISNUMBER(SEARCH("travel",'01_SKU_Input'!O9)),ISNUMBER(SEARCH("Premium",'01_SKU_Input'!O9)),ISNUMBER(SEARCH("Discovery",'01_SKU_Input'!O9)),ISNUMBER(SEARCH("Destination",'01_SKU_Input'!O9))),5,IF(OR(ISNUMBER(SEARCH("Impulse",'01_SKU_Input'!O9)),ISNUMBER(SEARCH("Replenishment",'01_SKU_Input'!O9)),ISNUMBER(SEARCH("Business",'01_SKU_Input'!O9))),4,3)) -> 5 | N9: =IF(H9="Hero",5,IF(H9="Margin builder",5,IF(H9="Premiumiser",4,IF(H9="Recruitment SKU",4,IF(H9="Traffic driver",3,IF(H9="Seasonal/test SKU",3,1)))))) -> 3 | O9: =IF('01_SKU_Input'!Q9="High",-10,IF('01_SKU_Input'!Q9="Medium",-5,0)) -> -5 | P9: =I9*'02_Assumptions'!$B$4/5*100+J9*'02_Assumptions'!$B$5/5*100+K9*'02_Assumptions'!$B$6/5*100+L9*'02_Assumptions'!$B$7/5*100+M9*'02_Assumptions'!$B$8/5*100+N9*'02_Assumptions'!$B$9/5*100+O9 -> 44 | Q9: =I9*20/5+J9*20/5+K9*15/5 -> 30 | R9: =L9*15/5+M9*10/5+N9*10/5+O9 -> 14 | S9: =IF(AND(P9>=65,J9>=4,K9>=4,O9>=-5),"Invest",IF(AND(P9>=40,G9<60%,OR(H9="Recruitment SKU",H9="Seasonal/test SKU")),"Test",IF(P9>=50,"Retain","Remove"))) -> Test | T9: =IF(AND(Q9>=35,R9>=20),"Winners",IF(AND(Q9>=35,R9<20),"Efficient but not priority",IF(AND(Q9<35,R9>=20),"Potential bets","Weak tail"))) -> Weak tail
A10: ='01_SKU_Input'!A10 -> SKU 07 | B10: ='01_SKU_Input'!B10 -> Botanika Mini Fragrance Set | C10: ='01_SKU_Input'!C10 -> Beauty | D10: ='01_SKU_Input'!H10 -> 245000 | E10: ='01_SKU_Input'!I10 -> 0.67 | F10: ='01_SKU_Input'!L10 -> 31 | G10: ='01_SKU_Input'!M10 -> 0.34 | H10: ='01_SKU_Input'!R10 -> Recruitment SKU | I10: =IF(D10>=350000,5,IF(D10>=260000,4,IF(D10>=170000,3,IF(D10>=100000,2,1)))) -> 3 | J10: =IF(E10>=60%,5,IF(E10>=50%,4,IF(E10>=40%,3,IF(E10>=30%,2,1)))) -> 5 | K10: =IF(F10>=75,5,IF(F10>=55,4,IF(F10>=35,3,IF(F10>=20,2,1)))) -> 2 | L10: =IF(AND(K10>=4,G10<60%),5,IF(AND(K10>=4,G10<80%),4,IF(AND(K10>=3,G10<80%),3,IF(AND(K10<=2,G10>=75%),2,1)))) -> 1 | M10: =IF(OR(ISNUMBER(SEARCH("Gift",'01_SKU_Input'!O10)),ISNUMBER(SEARCH("travel",'01_SKU_Input'!O10)),ISNUMBER(SEARCH("Premium",'01_SKU_Input'!O10)),ISNUMBER(SEARCH("Discovery",'01_SKU_Input'!O10)),ISNUMBER(SEARCH("Destination",'01_SKU_Input'!O10))),5,IF(OR(ISNUMBER(SEARCH("Impulse",'01_SKU_Input'!O10)),ISNUMBER(SEARCH("Replenishment",'01_SKU_Input'!O10)),ISNUMBER(SEARCH("Business",'01_SKU_Input'!O10))),4,3)) -> 5 | N10: =IF(H10="Hero",5,IF(H10="Margin builder",5,IF(H10="Premiumiser",4,IF(H10="Recruitment SKU",4,IF(H10="Traffic driver",3,IF(H10="Seasonal/test SKU",3,1)))))) -> 4 | O10: =IF('01_SKU_Input'!Q10="High",-10,IF('01_SKU_Input'!Q10="Medium",-5,0)) -> 0 | P10: =I10*'02_Assumptions'!$B$4/5*100+J10*'02_Assumptions'!$B$5/5*100+K10*'02_Assumptions'!$B$6/5*100+L10*'02_Assumptions'!$B$7/5*100+M10*'02_Assumptions'!$B$8/5*100+N10*'02_Assumptions'!$B$9/5*100+O10 -> 59 | Q10: =I10*20/5+J10*20/5+K10*15/5 -> 38 | R10: =L10*15/5+M10*10/5+N10*10/5+O10 -> 21 | S10: =IF(AND(P10>=65,J10>=4,K10>=4,O10>=-5),"Invest",IF(AND(P10>=40,G10<60%,OR(H10="Recruitment SKU",H10="Seasonal/test SKU")),"Test",IF(P10>=50,"Retain","Remove"))) -> Test | T10: =IF(AND(Q10>=35,R10>=20),"Winners",IF(AND(Q10>=35,R10<20),"Efficient but not priority",IF(AND(Q10<35,R10>=20),"Potential bets","Weak tail"))) -> Winners
A11: ='01_SKU_Input'!A11 -> SKU 08 | B11: ='01_SKU_Input'!B11 -> Frost Mints Pocket Pack | C11: ='01_SKU_Input'!C11 -> Confectionery | D11: ='01_SKU_Input'!H11 -> 95000 | E11: ='01_SKU_Input'!I11 -> 0.29 | F11: ='01_SKU_Input'!L11 -> 64 | G11: ='01_SKU_Input'!M11 -> 0.91 | H11: ='01_SKU_Input'!R11 -> Traffic driver | I11: =IF(D11>=350000,5,IF(D11>=260000,4,IF(D11>=170000,3,IF(D11>=100000,2,1)))) -> 1 | J11: =IF(E11>=60%,5,IF(E11>=50%,4,IF(E11>=40%,3,IF(E11>=30%,2,1)))) -> 1 | K11: =IF(F11>=75,5,IF(F11>=55,4,IF(F11>=35,3,IF(F11>=20,2,1)))) -> 4 | L11: =IF(AND(K11>=4,G11<60%),5,IF(AND(K11>=4,G11<80%),4,IF(AND(K11>=3,G11<80%),3,IF(AND(K11<=2,G11>=75%),2,1)))) -> 1 | M11: =IF(OR(ISNUMBER(SEARCH("Gift",'01_SKU_Input'!O11)),ISNUMBER(SEARCH("travel",'01_SKU_Input'!O11)),ISNUMBER(SEARCH("Premium",'01_SKU_Input'!O11)),ISNUMBER(SEARCH("Discovery",'01_SKU_Input'!O11)),ISNUMBER(SEARCH("Destination",'01_SKU_Input'!O11))),5,IF(OR(ISNUMBER(SEARCH("Impulse",'01_SKU_Input'!O11)),ISNUMBER(SEARCH("Replenishment",'01_SKU_Input'!O11)),ISNUMBER(SEARCH("Business",'01_SKU_Input'!O11))),4,3)) -> 4 | N11: =IF(H11="Hero",5,IF(H11="Margin builder",5,IF(H11="Premiumiser",4,IF(H11="Recruitment SKU",4,IF(H11="Traffic driver",3,IF(H11="Seasonal/test SKU",3,1)))))) -> 3 | O11: =IF('01_SKU_Input'!Q11="High",-10,IF('01_SKU_Input'!Q11="Medium",-5,0)) -> -10 | P11: =I11*'02_Assumptions'!$B$4/5*100+J11*'02_Assumptions'!$B$5/5*100+K11*'02_Assumptions'!$B$6/5*100+L11*'02_Assumptions'!$B$7/5*100+M11*'02_Assumptions'!$B$8/5*100+N11*'02_Assumptions'!$B$9/5*100+O11 -> 27 | Q11: =I11*20/5+J11*20/5+K11*15/5 -> 20 | R11: =L11*15/5+M11*10/5+N11*10/5+O11 -> 7 | S11: =IF(AND(P11>=65,J11>=4,K11>=4,O11>=-5),"Invest",IF(AND(P11>=40,G11<60%,OR(H11="Recruitment SKU",H11="Seasonal/test SKU")),"Test",IF(P11>=50,"Retain","Remove"))) -> Remove | T11: =IF(AND(Q11>=35,R11>=20),"Winners",IF(AND(Q11>=35,R11<20),"Efficient but not priority",IF(AND(Q11<35,R11>=20),"Potential bets","Weak tail"))) -> Weak tail
A12: ='01_SKU_Input'!A12 -> SKU 09 | B12: ='01_SKU_Input'!B12 -> Altitude Protein Bar 12-pack | C12: ='01_SKU_Input'!C12 -> Snacks | D12: ='01_SKU_Input'!H12 -> 165000 | E12: ='01_SKU_Input'!I12 -> 0.41 | F12: ='01_SKU_Input'!L12 -> 22 | G12: ='01_SKU_Input'!M12 -> 0.44 | H12: ='01_SKU_Input'!R12 -> Seasonal/test SKU | I12: =IF(D12>=350000,5,IF(D12>=260000,4,IF(D12>=170000,3,IF(D12>=100000,2,1)))) -> 2 | J12: =IF(E12>=60%,5,IF(E12>=50%,4,IF(E12>=40%,3,IF(E12>=30%,2,1)))) -> 3 | K12: =IF(F12>=75,5,IF(F12>=55,4,IF(F12>=35,3,IF(F12>=20,2,1)))) -> 2 | L12: =IF(AND(K12>=4,G12<60%),5,IF(AND(K12>=4,G12<80%),4,IF(AND(K12>=3,G12<80%),3,IF(AND(K12<=2,G12>=75%),2,1)))) -> 1 | M12: =IF(OR(ISNUMBER(SEARCH("Gift",'01_SKU_Input'!O12)),ISNUMBER(SEARCH("travel",'01_SKU_Input'!O12)),ISNUMBER(SEARCH("Premium",'01_SKU_Input'!O12)),ISNUMBER(SEARCH("Discovery",'01_SKU_Input'!O12)),ISNUMBER(SEARCH("Destination",'01_SKU_Input'!O12))),5,IF(OR(ISNUMBER(SEARCH("Impulse",'01_SKU_Input'!O12)),ISNUMBER(SEARCH("Replenishment",'01_SKU_Input'!O12)),ISNUMBER(SEARCH("Business",'01_SKU_Input'!O12))),4,3)) -> 5 | N12: =IF(H12="Hero",5,IF(H12="Margin builder",5,IF(H12="Premiumiser",4,IF(H12="Recruitment SKU",4,IF(H12="Traffic driver",3,IF(H12="Seasonal/test SKU",3,1)))))) -> 3 | O12: =IF('01_SKU_Input'!Q12="High",-10,IF('01_SKU_Input'!Q12="Medium",-5,0)) -> -5 | P12: =I12*'02_Assumptions'!$B$4/5*100+J12*'02_Assumptions'!$B$5/5*100+K12*'02_Assumptions'!$B$6/5*100+L12*'02_Assumptions'!$B$7/5*100+M12*'02_Assumptions'!$B$8/5*100+N12*'02_Assumptions'!$B$9/5*100+O12 -> 40 | Q12: =I12*20/5+J12*20/5+K12*15/5 -> 26 | R12: =L12*15/5+M12*10/5+N12*10/5+O12 -> 14 | S12: =IF(AND(P12>=65,J12>=4,K12>=4,O12>=-5),"Invest",IF(AND(P12>=40,G12<60%,OR(H12="Recruitment SKU",H12="Seasonal/test SKU")),"Test",IF(P12>=50,"Retain","Remove"))) -> Test | T12: =IF(AND(Q12>=35,R12>=20),"Winners",IF(AND(Q12>=35,R12<20),"Efficient but not priority",IF(AND(Q12<35,R12>=20),"Potential bets","Weak tail"))) -> Weak tail
A13: ='01_SKU_Input'!A13 -> SKU 10 | B13: ='01_SKU_Input'!B13 -> Mare RTD Cocktail 4x200ml | C13: ='01_SKU_Input'!C13 -> Beverage | D13: ='01_SKU_Input'!H13 -> 305000 | E13: ='01_SKU_Input'!I13 -> 0.51 | F13: ='01_SKU_Input'!L13 -> 57 | G13: ='01_SKU_Input'!M13 -> 0.39 | H13: ='01_SKU_Input'!R13 -> Premiumiser | I13: =IF(D13>=350000,5,IF(D13>=260000,4,IF(D13>=170000,3,IF(D13>=100000,2,1)))) -> 4 | J13: =IF(E13>=60%,5,IF(E13>=50%,4,IF(E13>=40%,3,IF(E13>=30%,2,1)))) -> 4 | K13: =IF(F13>=75,5,IF(F13>=55,4,IF(F13>=35,3,IF(F13>=20,2,1)))) -> 4 | L13: =IF(AND(K13>=4,G13<60%),5,IF(AND(K13>=4,G13<80%),4,IF(AND(K13>=3,G13<80%),3,IF(AND(K13<=2,G13>=75%),2,1)))) -> 5 | M13: =IF(OR(ISNUMBER(SEARCH("Gift",'01_SKU_Input'!O13)),ISNUMBER(SEARCH("travel",'01_SKU_Input'!O13)),ISNUMBER(SEARCH("Premium",'01_SKU_Input'!O13)),ISNUMBER(SEARCH("Discovery",'01_SKU_Input'!O13)),ISNUMBER(SEARCH("Destination",'01_SKU_Input'!O13))),5,IF(OR(ISNUMBER(SEARCH("Impulse",'01_SKU_Input'!O13)),ISNUMBER(SEARCH("Replenishment",'01_SKU_Input'!O13)),ISNUMBER(SEARCH("Business",'01_SKU_Input'!O13))),4,3)) -> 5 | N13: =IF(H13="Hero",5,IF(H13="Margin builder",5,IF(H13="Premiumiser",4,IF(H13="Recruitment SKU",4,IF(H13="Traffic driver",3,IF(H13="Seasonal/test SKU",3,1)))))) -> 4 | O13: =IF('01_SKU_Input'!Q13="High",-10,IF('01_SKU_Input'!Q13="Medium",-5,0)) -> 0 | P13: =I13*'02_Assumptions'!$B$4/5*100+J13*'02_Assumptions'!$B$5/5*100+K13*'02_Assumptions'!$B$6/5*100+L13*'02_Assumptions'!$B$7/5*100+M13*'02_Assumptions'!$B$8/5*100+N13*'02_Assumptions'!$B$9/5*100+O13 -> 77 | Q13: =I13*20/5+J13*20/5+K13*15/5 -> 44 | R13: =L13*15/5+M13*10/5+N13*10/5+O13 -> 33 | S13: =IF(AND(P13>=65,J13>=4,K13>=4,O13>=-5),"Invest",IF(AND(P13>=40,G13<60%,OR(H13="Recruitment SKU",H13="Seasonal/test SKU")),"Test",IF(P13>=50,"Retain","Remove"))) -> Invest | T13: =IF(AND(Q13>=35,R13>=20),"Winners",IF(AND(Q13>=35,R13<20),"Efficient but not priority",IF(AND(Q13<35,R13>=20),"Potential bets","Weak tail"))) -> Winners
A14: ='01_SKU_Input'!A14 -> SKU 11 | B14: ='01_SKU_Input'!B14 -> Lumina Beauty Refill Pouch | C14: ='01_SKU_Input'!C14 -> Beauty | D14: ='01_SKU_Input'!H14 -> 120000 | E14: ='01_SKU_Input'!I14 -> 0.48 | F14: ='01_SKU_Input'!L14 -> 18 | G14: ='01_SKU_Input'!M14 -> 0.62 | H14: ='01_SKU_Input'!R14 -> Duplicative SKU | I14: =IF(D14>=350000,5,IF(D14>=260000,4,IF(D14>=170000,3,IF(D14>=100000,2,1)))) -> 2 | J14: =IF(E14>=60%,5,IF(E14>=50%,4,IF(E14>=40%,3,IF(E14>=30%,2,1)))) -> 3 | K14: =IF(F14>=75,5,IF(F14>=55,4,IF(F14>=35,3,IF(F14>=20,2,1)))) -> 1 | L14: =IF(AND(K14>=4,G14<60%),5,IF(AND(K14>=4,G14<80%),4,IF(AND(K14>=3,G14<80%),3,IF(AND(K14<=2,G14>=75%),2,1)))) -> 1 | M14: =IF(OR(ISNUMBER(SEARCH("Gift",'01_SKU_Input'!O14)),ISNUMBER(SEARCH("travel",'01_SKU_Input'!O14)),ISNUMBER(SEARCH("Premium",'01_SKU_Input'!O14)),ISNUMBER(SEARCH("Discovery",'01_SKU_Input'!O14)),ISNUMBER(SEARCH("Destination",'01_SKU_Input'!O14))),5,IF(OR(ISNUMBER(SEARCH("Impulse",'01_SKU_Input'!O14)),ISNUMBER(SEARCH("Replenishment",'01_SKU_Input'!O14)),ISNUMBER(SEARCH("Business",'01_SKU_Input'!O14))),4,3)) -> 4 | N14: =IF(H14="Hero",5,IF(H14="Margin builder",5,IF(H14="Premiumiser",4,IF(H14="Recruitment SKU",4,IF(H14="Traffic driver",3,IF(H14="Seasonal/test SKU",3,1)))))) -> 1 | O14: =IF('01_SKU_Input'!Q14="High",-10,IF('01_SKU_Input'!Q14="Medium",-5,0)) -> -5 | P14: =I14*'02_Assumptions'!$B$4/5*100+J14*'02_Assumptions'!$B$5/5*100+K14*'02_Assumptions'!$B$6/5*100+L14*'02_Assumptions'!$B$7/5*100+M14*'02_Assumptions'!$B$8/5*100+N14*'02_Assumptions'!$B$9/5*100+O14 -> 31 | Q14: =I14*20/5+J14*20/5+K14*15/5 -> 23 | R14: =L14*15/5+M14*10/5+N14*10/5+O14 -> 8 | S14: =IF(AND(P14>=65,J14>=4,K14>=4,O14>=-5),"Invest",IF(AND(P14>=40,G14<60%,OR(H14="Recruitment SKU",H14="Seasonal/test SKU")),"Test",IF(P14>=50,"Retain","Remove"))) -> Remove | T14: =IF(AND(Q14>=35,R14>=20),"Winners",IF(AND(Q14>=35,R14<20),"Efficient but not priority",IF(AND(Q14<35,R14>=20),"Potential bets","Weak tail"))) -> Weak tail
A15: ='01_SKU_Input'!A15 -> SKU 12 | B15: ='01_SKU_Input'!B15 -> Casa Roja Olive Oil Gift Tin | C15: ='01_SKU_Input'!C15 -> Food | D15: ='01_SKU_Input'!H15 -> 275000 | E15: ='01_SKU_Input'!I15 -> 0.53 | F15: ='01_SKU_Input'!L15 -> 35 | G15: ='01_SKU_Input'!M15 -> 0.46 | H15: ='01_SKU_Input'!R15 -> Margin builder | I15: =IF(D15>=350000,5,IF(D15>=260000,4,IF(D15>=170000,3,IF(D15>=100000,2,1)))) -> 4 | J15: =IF(E15>=60%,5,IF(E15>=50%,4,IF(E15>=40%,3,IF(E15>=30%,2,1)))) -> 4 | K15: =IF(F15>=75,5,IF(F15>=55,4,IF(F15>=35,3,IF(F15>=20,2,1)))) -> 3 | L15: =IF(AND(K15>=4,G15<60%),5,IF(AND(K15>=4,G15<80%),4,IF(AND(K15>=3,G15<80%),3,IF(AND(K15<=2,G15>=75%),2,1)))) -> 3 | M15: =IF(OR(ISNUMBER(SEARCH("Gift",'01_SKU_Input'!O15)),ISNUMBER(SEARCH("travel",'01_SKU_Input'!O15)),ISNUMBER(SEARCH("Premium",'01_SKU_Input'!O15)),ISNUMBER(SEARCH("Discovery",'01_SKU_Input'!O15)),ISNUMBER(SEARCH("Destination",'01_SKU_Input'!O15))),5,IF(OR(ISNUMBER(SEARCH("Impulse",'01_SKU_Input'!O15)),ISNUMBER(SEARCH("Replenishment",'01_SKU_Input'!O15)),ISNUMBER(SEARCH("Business",'01_SKU_Input'!O15))),4,3)) -> 5 | N15: =IF(H15="Hero",5,IF(H15="Margin builder",5,IF(H15="Premiumiser",4,IF(H15="Recruitment SKU",4,IF(H15="Traffic driver",3,IF(H15="Seasonal/test SKU",3,1)))))) -> 5 | O15: =IF('01_SKU_Input'!Q15="High",-10,IF('01_SKU_Input'!Q15="Medium",-5,0)) -> 0 | P15: =I15*'02_Assumptions'!$B$4/5*100+J15*'02_Assumptions'!$B$5/5*100+K15*'02_Assumptions'!$B$6/5*100+L15*'02_Assumptions'!$B$7/5*100+M15*'02_Assumptions'!$B$8/5*100+N15*'02_Assumptions'!$B$9/5*100+O15 -> 70 | Q15: =I15*20/5+J15*20/5+K15*15/5 -> 41 | R15: =L15*15/5+M15*10/5+N15*10/5+O15 -> 29 | S15: =IF(AND(P15>=65,J15>=4,K15>=4,O15>=-5),"Invest",IF(AND(P15>=40,G15<60%,OR(H15="Recruitment SKU",H15="Seasonal/test SKU")),"Test",IF(P15>=50,"Retain","Remove"))) -> Retain | T15: =IF(AND(Q15>=35,R15>=20),"Winners",IF(AND(Q15>=35,R15<20),"Efficient but not priority",IF(AND(Q15<35,R15>=20),"Potential bets","Weak tail"))) -> Winners

Sheet 04_Portfolio_Matrix
A1: Portfolio Matrix
A3: SKU | B3: Commercial Performance | C3: Strategic Attractiveness | D3: Recommendation | E3: Quadrant | G3: Quadrant | H3: Meaning | I3: Primary action
A4: ='03_Scoring_Model'!B4 -> Aura Chocolates Travel Gift Box 300g | B4: ='03_Scoring_Model'!Q4 -> 48 | C4: ='03_Scoring_Model'!R4 -> 32 | D4: ='03_Scoring_Model'!S4 -> Invest | E4: ='03_Scoring_Model'!T4 -> Winners | G4: Winners | H4: High performance / high strategy | I4: Invest
A5: ='03_Scoring_Model'!B5 -> Northgate Whisky Reserve 1L | B5: ='03_Scoring_Model'!Q5 -> 49 | C5: ='03_Scoring_Model'!R5 -> 24 | D5: ='03_Scoring_Model'!S5 -> Retain | E5: ='03_Scoring_Model'!T5 -> Winners | G5: Efficient but not priority | H5: High performance / low strategy | I5: Retain
A6: ='03_Scoring_Model'!B6 -> Vela Skin Hydration Travel Duo | B6: ='03_Scoring_Model'!Q6 -> 49 | C6: ='03_Scoring_Model'!R6 -> 25 | D6: ='03_Scoring_Model'!S6 -> Retain | E6: ='03_Scoring_Model'!T6 -> Winners | G6: Potential bets | H6: Low performance / high strategy | I6: Test
A7: ='03_Scoring_Model'!B7 -> Pulse Energy Multipack 6x250ml | B7: ='03_Scoring_Model'!Q7 -> 35 | C7: ='03_Scoring_Model'!R7 -> 7 | D7: ='03_Scoring_Model'!S7 -> Remove | E7: ='03_Scoring_Model'!T7 -> Efficient but not priority | G7: Weak tail | H7: Low performance / low strategy | I7: Remove
A8: ='03_Scoring_Model'!B8 -> Solara SPF Travel Kit | B8: ='03_Scoring_Model'!Q8 -> 41 | C8: ='03_Scoring_Model'!R8 -> 25 | D8: ='03_Scoring_Model'!S8 -> Test | E8: ='03_Scoring_Model'!T8 -> Winners
A9: ='03_Scoring_Model'!B9 -> Terra Coffee Premium Tin 250g | B9: ='03_Scoring_Model'!Q9 -> 30 | C9: ='03_Scoring_Model'!R9 -> 14 | D9: ='03_Scoring_Model'!S9 -> Test | E9: ='03_Scoring_Model'!T9 -> Weak tail
A10: ='03_Scoring_Model'!B10 -> Botanika Mini Fragrance Set | B10: ='03_Scoring_Model'!Q10 -> 38 | C10: ='03_Scoring_Model'!R10 -> 21 | D10: ='03_Scoring_Model'!S10 -> Test | E10: ='03_Scoring_Model'!T10 -> Winners
A11: ='03_Scoring_Model'!B11 -> Frost Mints Pocket Pack | B11: ='03_Scoring_Model'!Q11 -> 20 | C11: ='03_Scoring_Model'!R11 -> 7 | D11: ='03_Scoring_Model'!S11 -> Remove | E11: ='03_Scoring_Model'!T11 -> Weak tail
A12: ='03_Scoring_Model'!B12 -> Altitude Protein Bar 12-pack | B12: ='03_Scoring_Model'!Q12 -> 26 | C12: ='03_Scoring_Model'!R12 -> 14 | D12: ='03_Scoring_Model'!S12 -> Test | E12: ='03_Scoring_Model'!T12 -> Weak tail
A13: ='03_Scoring_Model'!B13 -> Mare RTD Cocktail 4x200ml | B13: ='03_Scoring_Model'!Q13 -> 44 | C13: ='03_Scoring_Model'!R13 -> 33 | D13: ='03_Scoring_Model'!S13 -> Invest | E13: ='03_Scoring_Model'!T13 -> Winners
A14: ='03_Scoring_Model'!B14 -> Lumina Beauty Refill Pouch | B14: ='03_Scoring_Model'!Q14 -> 23 | C14: ='03_Scoring_Model'!R14 -> 8 | D14: ='03_Scoring_Model'!S14 -> Remove | E14: ='03_Scoring_Model'!T14 -> Weak tail
A15: ='03_Scoring_Model'!B15 -> Casa Roja Olive Oil Gift Tin | B15: ='03_Scoring_Model'!Q15 -> 41 | C15: ='03_Scoring_Model'!R15 -> 29 | D15: ='03_Scoring_Model'!S15 -> Retain | E15: ='03_Scoring_Model'!T15 -> Winners

Sheet 05_Recommendations
A1: Recommendations
A3: SKU | B3: Current Role | C3: Total Score | D3: Recommendation | E3: Reason | F3: Action | G3: Expected Impact | H3: Priority | I3: Owner | J3: Timing
A4: ='03_Scoring_Model'!B4 -> Aura Chocolates Travel Gift Box 300g | B4: ='03_Scoring_Model'!H4 -> Hero | C4: ='03_Scoring_Model'!P4 -> 80 | D4: ='03_Scoring_Model'!S4 -> Invest | E4: =IF(D4="Invest","Strong economics and clear Travel Retail role.",IF(D4="Test","Strategic fit or distribution headroom, but needs proof.",IF(D4="Retain","Useful portfolio role; keep without over-investing.","Weak economics or distinctiveness; rationalise."))) -> Strong economics and clear Travel Retail role. | F4: =IF(D4="Invest","Expand distribution and visibility; build into buyer sell-in story.",IF(D4="Test","Run controlled airport/customer test with fixed KPIs.",IF(D4="Retain","Keep listed and monitor performance by customer.","Remove from core portfolio and replace with higher-fit SKU."))) -> Expand distribution and visibility; build into buyer sell-in story. | G4: =IF(D4="Invest","Upside from distribution and basket attachment.",IF(D4="Test","Learning value plus controlled upside.",IF(D4="Retain","Protect stable sales without extra spend.","Reduce complexity and cannibalisation risk."))) -> Upside from distribution and basket attachment. | H4: =IF(D4="Invest","High",IF(D4="Remove","High",IF(D4="Test","Medium","Low"))) -> High | I4: =IF(D4="Invest","Commercial Lead",IF(D4="Test","Category Lead",IF(D4="Remove","Portfolio Lead","Account Lead"))) -> Commercial Lead | J4: =IF(D4="Invest","Next range review",IF(D4="Test","12-week pilot",IF(D4="Remove","Next reset","Ongoing"))) -> Next range review
A5: ='03_Scoring_Model'!B5 -> Northgate Whisky Reserve 1L | B5: ='03_Scoring_Model'!H5 -> Margin builder | C5: ='03_Scoring_Model'!P5 -> 73 | D5: ='03_Scoring_Model'!S5 -> Retain | E5: =IF(D5="Invest","Strong economics and clear Travel Retail role.",IF(D5="Test","Strategic fit or distribution headroom, but needs proof.",IF(D5="Retain","Useful portfolio role; keep without over-investing.","Weak economics or distinctiveness; rationalise."))) -> Useful portfolio role; keep without over-investing. | F5: =IF(D5="Invest","Expand distribution and visibility; build into buyer sell-in story.",IF(D5="Test","Run controlled airport/customer test with fixed KPIs.",IF(D5="Retain","Keep listed and monitor performance by customer.","Remove from core portfolio and replace with higher-fit SKU."))) -> Keep listed and monitor performance by customer. | G5: =IF(D5="Invest","Upside from distribution and basket attachment.",IF(D5="Test","Learning value plus controlled upside.",IF(D5="Retain","Protect stable sales without extra spend.","Reduce complexity and cannibalisation risk."))) -> Protect stable sales without extra spend. | H5: =IF(D5="Invest","High",IF(D5="Remove","High",IF(D5="Test","Medium","Low"))) -> Low | I5: =IF(D5="Invest","Commercial Lead",IF(D5="Test","Category Lead",IF(D5="Remove","Portfolio Lead","Account Lead"))) -> Account Lead | J5: =IF(D5="Invest","Next range review",IF(D5="Test","12-week pilot",IF(D5="Remove","Next reset","Ongoing"))) -> Ongoing
A6: ='03_Scoring_Model'!B6 -> Vela Skin Hydration Travel Duo | B6: ='03_Scoring_Model'!H6 -> Premiumiser | C6: ='03_Scoring_Model'!P6 -> 74 | D6: ='03_Scoring_Model'!S6 -> Retain | E6: =IF(D6="Invest","Strong economics and clear Travel Retail role.",IF(D6="Test","Strategic fit or distribution headroom, but needs proof.",IF(D6="Retain","Useful portfolio role; keep without over-investing.","Weak economics or distinctiveness; rationalise."))) -> Useful portfolio role; keep without over-investing. | F6: =IF(D6="Invest","Expand distribution and visibility; build into buyer sell-in story.",IF(D6="Test","Run controlled airport/customer test with fixed KPIs.",IF(D6="Retain","Keep listed and monitor performance by customer.","Remove from core portfolio and replace with higher-fit SKU."))) -> Keep listed and monitor performance by customer. | G6: =IF(D6="Invest","Upside from distribution and basket attachment.",IF(D6="Test","Learning value plus controlled upside.",IF(D6="Retain","Protect stable sales without extra spend.","Reduce complexity and cannibalisation risk."))) -> Protect stable sales without extra spend. | H6: =IF(D6="Invest","High",IF(D6="Remove","High",IF(D6="Test","Medium","Low"))) -> Low | I6: =IF(D6="Invest","Commercial Lead",IF(D6="Test","Category Lead",IF(D6="Remove","Portfolio Lead","Account Lead"))) -> Account Lead | J6: =IF(D6="Invest","Next range review",IF(D6="Test","12-week pilot",IF(D6="Remove","Next reset","Ongoing"))) -> Ongoing
A7: ='03_Scoring_Model'!B7 -> Pulse Energy Multipack 6x250ml | B7: ='03_Scoring_Model'!H7 -> Traffic driver | C7: ='03_Scoring_Model'!P7 -> 42 | D7: ='03_Scoring_Model'!S7 -> Remove | E7: =IF(D7="Invest","Strong economics and clear Travel Retail role.",IF(D7="Test","Strategic fit or distribution headroom, but needs proof.",IF(D7="Retain","Useful portfolio role; keep without over-investing.","Weak economics or distinctiveness; rationalise."))) -> Weak economics or distinctiveness; rationalise. | F7: =IF(D7="Invest","Expand distribution and visibility; build into buyer sell-in story.",IF(D7="Test","Run controlled airport/customer test with fixed KPIs.",IF(D7="Retain","Keep listed and monitor performance by customer.","Remove from core portfolio and replace with higher-fit SKU."))) -> Remove from core portfolio and replace with higher-fit SKU. | G7: =IF(D7="Invest","Upside from distribution and basket attachment.",IF(D7="Test","Learning value plus controlled upside.",IF(D7="Retain","Protect stable sales without extra spend.","Reduce complexity and cannibalisation risk."))) -> Reduce complexity and cannibalisation risk. | H7: =IF(D7="Invest","High",IF(D7="Remove","High",IF(D7="Test","Medium","Low"))) -> High | I7: =IF(D7="Invest","Commercial Lead",IF(D7="Test","Category Lead",IF(D7="Remove","Portfolio Lead","Account Lead"))) -> Portfolio Lead | J7: =IF(D7="Invest","Next range review",IF(D7="Test","12-week pilot",IF(D7="Remove","Next reset","Ongoing"))) -> Next reset
A8: ='03_Scoring_Model'!B8 -> Solara SPF Travel Kit | B8: ='03_Scoring_Model'!H8 -> Recruitment SKU | C8: ='03_Scoring_Model'!P8 -> 66 | D8: ='03_Scoring_Model'!S8 -> Test | E8: =IF(D8="Invest","Strong economics and clear Travel Retail role.",IF(D8="Test","Strategic fit or distribution headroom, but needs proof.",IF(D8="Retain","Useful portfolio role; keep without over-investing.","Weak economics or distinctiveness; rationalise."))) -> Strategic fit or distribution headroom, but needs proof. | F8: =IF(D8="Invest","Expand distribution and visibility; build into buyer sell-in story.",IF(D8="Test","Run controlled airport/customer test with fixed KPIs.",IF(D8="Retain","Keep listed and monitor performance by customer.","Remove from core portfolio and replace with higher-fit SKU."))) -> Run controlled airport/customer test with fixed KPIs. | G8: =IF(D8="Invest","Upside from distribution and basket attachment.",IF(D8="Test","Learning value plus controlled upside.",IF(D8="Retain","Protect stable sales without extra spend.","Reduce complexity and cannibalisation risk."))) -> Learning value plus controlled upside. | H8: =IF(D8="Invest","High",IF(D8="Remove","High",IF(D8="Test","Medium","Low"))) -> Medium | I8: =IF(D8="Invest","Commercial Lead",IF(D8="Test","Category Lead",IF(D8="Remove","Portfolio Lead","Account Lead"))) -> Category Lead | J8: =IF(D8="Invest","Next range review",IF(D8="Test","12-week pilot",IF(D8="Remove","Next reset","Ongoing"))) -> 12-week pilot
A9: ='03_Scoring_Model'!B9 -> Terra Coffee Premium Tin 250g | B9: ='03_Scoring_Model'!H9 -> Seasonal/test SKU | C9: ='03_Scoring_Model'!P9 -> 44 | D9: ='03_Scoring_Model'!S9 -> Test | E9: =IF(D9="Invest","Strong economics and clear Travel Retail role.",IF(D9="Test","Strategic fit or distribution headroom, but needs proof.",IF(D9="Retain","Useful portfolio role; keep without over-investing.","Weak economics or distinctiveness; rationalise."))) -> Strategic fit or distribution headroom, but needs proof. | F9: =IF(D9="Invest","Expand distribution and visibility; build into buyer sell-in story.",IF(D9="Test","Run controlled airport/customer test with fixed KPIs.",IF(D9="Retain","Keep listed and monitor performance by customer.","Remove from core portfolio and replace with higher-fit SKU."))) -> Run controlled airport/customer test with fixed KPIs. | G9: =IF(D9="Invest","Upside from distribution and basket attachment.",IF(D9="Test","Learning value plus controlled upside.",IF(D9="Retain","Protect stable sales without extra spend.","Reduce complexity and cannibalisation risk."))) -> Learning value plus controlled upside. | H9: =IF(D9="Invest","High",IF(D9="Remove","High",IF(D9="Test","Medium","Low"))) -> Medium | I9: =IF(D9="Invest","Commercial Lead",IF(D9="Test","Category Lead",IF(D9="Remove","Portfolio Lead","Account Lead"))) -> Category Lead | J9: =IF(D9="Invest","Next range review",IF(D9="Test","12-week pilot",IF(D9="Remove","Next reset","Ongoing"))) -> 12-week pilot
A10: ='03_Scoring_Model'!B10 -> Botanika Mini Fragrance Set | B10: ='03_Scoring_Model'!H10 -> Recruitment SKU | C10: ='03_Scoring_Model'!P10 -> 59 | D10: ='03_Scoring_Model'!S10 -> Test | E10: =IF(D10="Invest","Strong economics and clear Travel Retail role.",IF(D10="Test","Strategic fit or distribution headroom, but needs proof.",IF(D10="Retain","Useful portfolio role; keep without over-investing.","Weak economics or distinctiveness; rationalise."))) -> Strategic fit or distribution headroom, but needs proof. | F10: =IF(D10="Invest","Expand distribution and visibility; build into buyer sell-in story.",IF(D10="Test","Run controlled airport/customer test with fixed KPIs.",IF(D10="Retain","Keep listed and monitor performance by customer.","Remove from core portfolio and replace with higher-fit SKU."))) -> Run controlled airport/customer test with fixed KPIs. | G10: =IF(D10="Invest","Upside from distribution and basket attachment.",IF(D10="Test","Learning value plus controlled upside.",IF(D10="Retain","Protect stable sales without extra spend.","Reduce complexity and cannibalisation risk."))) -> Learning value plus controlled upside. | H10: =IF(D10="Invest","High",IF(D10="Remove","High",IF(D10="Test","Medium","Low"))) -> Medium | I10: =IF(D10="Invest","Commercial Lead",IF(D10="Test","Category Lead",IF(D10="Remove","Portfolio Lead","Account Lead"))) -> Category Lead | J10: =IF(D10="Invest","Next range review",IF(D10="Test","12-week pilot",IF(D10="Remove","Next reset","Ongoing"))) -> 12-week pilot
A11: ='03_Scoring_Model'!B11 -> Frost Mints Pocket Pack | B11: ='03_Scoring_Model'!H11 -> Traffic driver | C11: ='03_Scoring_Model'!P11 -> 27 | D11: ='03_Scoring_Model'!S11 -> Remove | E11: =IF(D11="Invest","Strong economics and clear Travel Retail role.",IF(D11="Test","Strategic fit or distribution headroom, but needs proof.",IF(D11="Retain","Useful portfolio role; keep without over-investing.","Weak economics or distinctiveness; rationalise."))) -> Weak economics or distinctiveness; rationalise. | F11: =IF(D11="Invest","Expand distribution and visibility; build into buyer sell-in story.",IF(D11="Test","Run controlled airport/customer test with fixed KPIs.",IF(D11="Retain","Keep listed and monitor performance by customer.","Remove from core portfolio and replace with higher-fit SKU."))) -> Remove from core portfolio and replace with higher-fit SKU. | G11: =IF(D11="Invest","Upside from distribution and basket attachment.",IF(D11="Test","Learning value plus controlled upside.",IF(D11="Retain","Protect stable sales without extra spend.","Reduce complexity and cannibalisation risk."))) -> Reduce complexity and cannibalisation risk. | H11: =IF(D11="Invest","High",IF(D11="Remove","High",IF(D11="Test","Medium","Low"))) -> High | I11: =IF(D11="Invest","Commercial Lead",IF(D11="Test","Category Lead",IF(D11="Remove","Portfolio Lead","Account Lead"))) -> Portfolio Lead | J11: =IF(D11="Invest","Next range review",IF(D11="Test","12-week pilot",IF(D11="Remove","Next reset","Ongoing"))) -> Next reset
A12: ='03_Scoring_Model'!B12 -> Altitude Protein Bar 12-pack | B12: ='03_Scoring_Model'!H12 -> Seasonal/test SKU | C12: ='03_Scoring_Model'!P12 -> 40 | D12: ='03_Scoring_Model'!S12 -> Test | E12: =IF(D12="Invest","Strong economics and clear Travel Retail role.",IF(D12="Test","Strategic fit or distribution headroom, but needs proof.",IF(D12="Retain","Useful portfolio role; keep without over-investing.","Weak economics or distinctiveness; rationalise."))) -> Strategic fit or distribution headroom, but needs proof. | F12: =IF(D12="Invest","Expand distribution and visibility; build into buyer sell-in story.",IF(D12="Test","Run controlled airport/customer test with fixed KPIs.",IF(D12="Retain","Keep listed and monitor performance by customer.","Remove from core portfolio and replace with higher-fit SKU."))) -> Run controlled airport/customer test with fixed KPIs. | G12: =IF(D12="Invest","Upside from distribution and basket attachment.",IF(D12="Test","Learning value plus controlled upside.",IF(D12="Retain","Protect stable sales without extra spend.","Reduce complexity and cannibalisation risk."))) -> Learning value plus controlled upside. | H12: =IF(D12="Invest","High",IF(D12="Remove","High",IF(D12="Test","Medium","Low"))) -> Medium | I12: =IF(D12="Invest","Commercial Lead",IF(D12="Test","Category Lead",IF(D12="Remove","Portfolio Lead","Account Lead"))) -> Category Lead | J12: =IF(D12="Invest","Next range review",IF(D12="Test","12-week pilot",IF(D12="Remove","Next reset","Ongoing"))) -> 12-week pilot
A13: ='03_Scoring_Model'!B13 -> Mare RTD Cocktail 4x200ml | B13: ='03_Scoring_Model'!H13 -> Premiumiser | C13: ='03_Scoring_Model'!P13 -> 77 | D13: ='03_Scoring_Model'!S13 -> Invest | E13: =IF(D13="Invest","Strong economics and clear Travel Retail role.",IF(D13="Test","Strategic fit or distribution headroom, but needs proof.",IF(D13="Retain","Useful portfolio role; keep without over-investing.","Weak economics or distinctiveness; rationalise."))) -> Strong economics and clear Travel Retail role. | F13: =IF(D13="Invest","Expand distribution and visibility; build into buyer sell-in story.",IF(D13="Test","Run controlled airport/customer test with fixed KPIs.",IF(D13="Retain","Keep listed and monitor performance by customer.","Remove from core portfolio and replace with higher-fit SKU."))) -> Expand distribution and visibility; build into buyer sell-in story. | G13: =IF(D13="Invest","Upside from distribution and basket attachment.",IF(D13="Test","Learning value plus controlled upside.",IF(D13="Retain","Protect stable sales without extra spend.","Reduce complexity and cannibalisation risk."))) -> Upside from distribution and basket attachment. | H13: =IF(D13="Invest","High",IF(D13="Remove","High",IF(D13="Test","Medium","Low"))) -> High | I13: =IF(D13="Invest","Commercial Lead",IF(D13="Test","Category Lead",IF(D13="Remove","Portfolio Lead","Account Lead"))) -> Commercial Lead | J13: =IF(D13="Invest","Next range review",IF(D13="Test","12-week pilot",IF(D13="Remove","Next reset","Ongoing"))) -> Next range review
A14: ='03_Scoring_Model'!B14 -> Lumina Beauty Refill Pouch | B14: ='03_Scoring_Model'!H14 -> Duplicative SKU | C14: ='03_Scoring_Model'!P14 -> 31 | D14: ='03_Scoring_Model'!S14 -> Remove | E14: =IF(D14="Invest","Strong economics and clear Travel Retail role.",IF(D14="Test","Strategic fit or distribution headroom, but needs proof.",IF(D14="Retain","Useful portfolio role; keep without over-investing.","Weak economics or distinctiveness; rationalise."))) -> Weak economics or distinctiveness; rationalise. | F14: =IF(D14="Invest","Expand distribution and visibility; build into buyer sell-in story.",IF(D14="Test","Run controlled airport/customer test with fixed KPIs.",IF(D14="Retain","Keep listed and monitor performance by customer.","Remove from core portfolio and replace with higher-fit SKU."))) -> Remove from core portfolio and replace with higher-fit SKU. | G14: =IF(D14="Invest","Upside from distribution and basket attachment.",IF(D14="Test","Learning value plus controlled upside.",IF(D14="Retain","Protect stable sales without extra spend.","Reduce complexity and cannibalisation risk."))) -> Reduce complexity and cannibalisation risk. | H14: =IF(D14="Invest","High",IF(D14="Remove","High",IF(D14="Test","Medium","Low"))) -> High | I14: =IF(D14="Invest","Commercial Lead",IF(D14="Test","Category Lead",IF(D14="Remove","Portfolio Lead","Account Lead"))) -> Portfolio Lead | J14: =IF(D14="Invest","Next range review",IF(D14="Test","12-week pilot",IF(D14="Remove","Next reset","Ongoing"))) -> Next reset
A15: ='03_Scoring_Model'!B15 -> Casa Roja Olive Oil Gift Tin | B15: ='03_Scoring_Model'!H15 -> Margin builder | C15: ='03_Scoring_Model'!P15 -> 70 | D15: ='03_Scoring_Model'!S15 -> Retain | E15: =IF(D15="Invest","Strong economics and clear Travel Retail role.",IF(D15="Test","Strategic fit or distribution headroom, but needs proof.",IF(D15="Retain","Useful portfolio role; keep without over-investing.","Weak economics or distinctiveness; rationalise."))) -> Useful portfolio role; keep without over-investing. | F15: =IF(D15="Invest","Expand distribution and visibility; build into buyer sell-in story.",IF(D15="Test","Run controlled airport/customer test with fixed KPIs.",IF(D15="Retain","Keep listed and monitor performance by customer.","Remove from core portfolio and replace with higher-fit SKU."))) -> Keep listed and monitor performance by customer. | G15: =IF(D15="Invest","Upside from distribution and basket attachment.",IF(D15="Test","Learning value plus controlled upside.",IF(D15="Retain","Protect stable sales without extra spend.","Reduce complexity and cannibalisation risk."))) -> Protect stable sales without extra spend. | H15: =IF(D15="Invest","High",IF(D15="Remove","High",IF(D15="Test","Medium","Low"))) -> Low | I15: =IF(D15="Invest","Commercial Lead",IF(D15="Test","Category Lead",IF(D15="Remove","Portfolio Lead","Account Lead"))) -> Account Lead | J15: =IF(D15="Invest","Next range review",IF(D15="Test","12-week pilot",IF(D15="Remove","Next reset","Ongoing"))) -> Ongoing

Sheet 06_Scenario_Test
A1: Scenario Test
A3: Scenario | B3: SKU | C3: Change | D3: Assumption | E3: New Sales | F3: New Margin | G3: New Score | H3: Recommendation Change | I3: Comment
A4: Increase distribution of Mare RTD Cocktail 4x200ml | B4: Mare RTD Cocktail 4x200ml | C4: Distribution +20% | D4: 0.2 | E4: =IFERROR(INDEX('01_SKU_Input'!$H$4:$H$15,MATCH(B4,'01_SKU_Input'!$B$4:$B$15,0))*(1+IF(ISNUMBER(SEARCH("Distribution",C4)),D4,IF(ISNUMBER(SEARCH("Visibility",C4)),D4,0))),"") -> 366000 | F4: =IFERROR(INDEX('01_SKU_Input'!$I$4:$I$15,MATCH(B4,'01_SKU_Input'!$B$4:$B$15,0))+IF(ISNUMBER(SEARCH("Margin",C4)),D4,0),"") -> 0.51 | G4: =IFERROR(INDEX('03_Scoring_Model'!$P$4:$P$15,MATCH(B4,'03_Scoring_Model'!$B$4:$B$15,0))+IF(ISNUMBER(SEARCH("Distribution",C4)),4,IF(ISNUMBER(SEARCH("Visibility",C4)),3,IF(ISNUMBER(SEARCH("Margin",C4)),3,IF(ISNUMBER(SEARCH("transfer",C4)),-5,0)))),"") -> 81 | H4: =IFERROR(INDEX('03_Scoring_Model'!$S$4:$S$15,MATCH(B4,'03_Scoring_Model'!$B$4:$B$15,0))&" -> "&IF(G4>=65,"Invest",IF(G4>=50,"Test/Retain","Remove")),"") -> Invest -> Invest | I4: Tests whether premium RTD can scale beyond current doors
A5: Remove low-performing duplicate SKU | B5: Lumina Beauty Refill Pouch | C5: Remove and transfer 30% sales | D5: 0.3 | E5: =IFERROR(INDEX('01_SKU_Input'!$H$4:$H$15,MATCH(B5,'01_SKU_Input'!$B$4:$B$15,0))*(1+IF(ISNUMBER(SEARCH("Distribution",C5)),D5,IF(ISNUMBER(SEARCH("Visibility",C5)),D5,0))),"") -> 120000 | F5: =IFERROR(INDEX('01_SKU_Input'!$I$4:$I$15,MATCH(B5,'01_SKU_Input'!$B$4:$B$15,0))+IF(ISNUMBER(SEARCH("Margin",C5)),D5,0),"") -> 0.48 | G5: =IFERROR(INDEX('03_Scoring_Model'!$P$4:$P$15,MATCH(B5,'03_Scoring_Model'!$B$4:$B$15,0))+IF(ISNUMBER(SEARCH("Distribution",C5)),4,IF(ISNUMBER(SEARCH("Visibility",C5)),3,IF(ISNUMBER(SEARCH("Margin",C5)),3,IF(ISNUMBER(SEARCH("transfer",C5)),-5,0)))),"") -> 26 | H5: =IFERROR(INDEX('03_Scoring_Model'!$S$4:$S$15,MATCH(B5,'03_Scoring_Model'!$B$4:$B$15,0))&" -> "&IF(G5>=65,"Invest",IF(G5>=50,"Test/Retain","Remove")),"") -> Remove -> Remove | I5: Assumes partial sales transfer to stronger beauty SKUs
A6: Test Botanika Mini Fragrance Set in high-tourism airports | B6: Botanika Mini Fragrance Set | C6: Distribution +25% | D6: 0.25 | E6: =IFERROR(INDEX('01_SKU_Input'!$H$4:$H$15,MATCH(B6,'01_SKU_Input'!$B$4:$B$15,0))*(1+IF(ISNUMBER(SEARCH("Distribution",C6)),D6,IF(ISNUMBER(SEARCH("Visibility",C6)),D6,0))),"") -> 306250 | F6: =IFERROR(INDEX('01_SKU_Input'!$I$4:$I$15,MATCH(B6,'01_SKU_Input'!$B$4:$B$15,0))+IF(ISNUMBER(SEARCH("Margin",C6)),D6,0),"") -> 0.67 | G6: =IFERROR(INDEX('03_Scoring_Model'!$P$4:$P$15,MATCH(B6,'03_Scoring_Model'!$B$4:$B$15,0))+IF(ISNUMBER(SEARCH("Distribution",C6)),4,IF(ISNUMBER(SEARCH("Visibility",C6)),3,IF(ISNUMBER(SEARCH("Margin",C6)),3,IF(ISNUMBER(SEARCH("transfer",C6)),-5,0)))),"") -> 63 | H6: =IFERROR(INDEX('03_Scoring_Model'!$S$4:$S$15,MATCH(B6,'03_Scoring_Model'!$B$4:$B$15,0))&" -> "&IF(G6>=65,"Invest",IF(G6>=50,"Test/Retain","Remove")),"") -> Test -> Test/Retain | I6: Controlled test for discovery-led beauty purchase
A7: Invest in Northgate Whisky Reserve 1L | B7: Northgate Whisky Reserve 1L | C7: Visibility +10% ROS | D7: 0.1 | E7: =IFERROR(INDEX('01_SKU_Input'!$H$4:$H$15,MATCH(B7,'01_SKU_Input'!$B$4:$B$15,0))*(1+IF(ISNUMBER(SEARCH("Distribution",C7)),D7,IF(ISNUMBER(SEARCH("Visibility",C7)),D7,0))),"") -> 561000 | F7: =IFERROR(INDEX('01_SKU_Input'!$I$4:$I$15,MATCH(B7,'01_SKU_Input'!$B$4:$B$15,0))+IF(ISNUMBER(SEARCH("Margin",C7)),D7,0),"") -> 0.62 | G7: =IFERROR(INDEX('03_Scoring_Model'!$P$4:$P$15,MATCH(B7,'03_Scoring_Model'!$B$4:$B$15,0))+IF(ISNUMBER(SEARCH("Distribution",C7)),4,IF(ISNUMBER(SEARCH("Visibility",C7)),3,IF(ISNUMBER(SEARCH("Margin",C7)),3,IF(ISNUMBER(SEARCH("transfer",C7)),-5,0)))),"") -> 76 | H7: =IFERROR(INDEX('03_Scoring_Model'!$S$4:$S$15,MATCH(B7,'03_Scoring_Model'!$B$4:$B$15,0))&" -> "&IF(G7>=65,"Invest",IF(G7>=50,"Test/Retain","Remove")),"") -> Retain -> Invest | I7: Targets gifting-heavy locations and premium shoppers
A8: Margin improvement on Pulse multipack | B8: Pulse Energy Multipack 6x250ml | C8: Margin +3 pts | D8: 0.03 | E8: =IFERROR(INDEX('01_SKU_Input'!$H$4:$H$15,MATCH(B8,'01_SKU_Input'!$B$4:$B$15,0))*(1+IF(ISNUMBER(SEARCH("Distribution",C8)),D8,IF(ISNUMBER(SEARCH("Visibility",C8)),D8,0))),"") -> 210000 | F8: =IFERROR(INDEX('01_SKU_Input'!$I$4:$I$15,MATCH(B8,'01_SKU_Input'!$B$4:$B$15,0))+IF(ISNUMBER(SEARCH("Margin",C8)),D8,0),"") -> 0.39 | G8: =IFERROR(INDEX('03_Scoring_Model'!$P$4:$P$15,MATCH(B8,'03_Scoring_Model'!$B$4:$B$15,0))+IF(ISNUMBER(SEARCH("Distribution",C8)),4,IF(ISNUMBER(SEARCH("Visibility",C8)),3,IF(ISNUMBER(SEARCH("Margin",C8)),3,IF(ISNUMBER(SEARCH("transfer",C8)),-5,0)))),"") -> 45 | H8: =IFERROR(INDEX('03_Scoring_Model'!$S$4:$S$15,MATCH(B8,'03_Scoring_Model'!$B$4:$B$15,0))&" -> "&IF(G8>=65,"Invest",IF(G8>=50,"Test/Retain","Remove")),"") -> Remove -> Remove | I8: Tests whether stronger terms repair economics
